celestialtk/__init__.py
celestialtk/floating_points.py
celestialtk-0.1.0.dist-info/LICENSE
celestialtk-0.1.0.dist-info/METADATA
celestialtk-0.1.0.dist-info/WHEEL
celestialtk-0.1.0.dist-info/top_level.txt
celestialtk-0.1.0.dist-info/RECORD
