Metadata-Version: 2.1
Name: celestialtk
Version: 0.1.0
Summary: A Tkinter animation library for celestial-like floating points
Home-page: https://github.com/ricardious
Download-URL: https://github.com/ricardious/celestialtk.git
Author: Alex Ricardo Castañeda Rodríguez
Author-email: castaneda.systems@gmail.com
Keywords: tkinter animation visualization
Classifier: Programming Language :: Python :: 3
Classifier: License :: OSI Approved :: MIT License
Classifier: Operating System :: OS Independent
Classifier: Topic :: Software Development :: Libraries :: Python Modules
Classifier: Topic :: Multimedia :: Graphics
Requires-Python: >=3.6
License-File: LICENSE
